odoo/addons/base_search_mail_content/README.rst
odoo/addons/base_search_mail_content/__init__.py
odoo/addons/base_search_mail_content/__manifest__.py
odoo/addons/base_search_mail_content/data/trgm_index_data.xml
odoo/addons/base_search_mail_content/i18n/am.po
odoo/addons/base_search_mail_content/i18n/ar.po
odoo/addons/base_search_mail_content/i18n/base_search_mail_content.pot
odoo/addons/base_search_mail_content/i18n/bg.po
odoo/addons/base_search_mail_content/i18n/bs.po
odoo/addons/base_search_mail_content/i18n/ca.po
odoo/addons/base_search_mail_content/i18n/cs.po
odoo/addons/base_search_mail_content/i18n/da.po
odoo/addons/base_search_mail_content/i18n/de.po
odoo/addons/base_search_mail_content/i18n/el_GR.po
odoo/addons/base_search_mail_content/i18n/en_GB.po
odoo/addons/base_search_mail_content/i18n/es.po
odoo/addons/base_search_mail_content/i18n/es_CR.po
odoo/addons/base_search_mail_content/i18n/es_EC.po
odoo/addons/base_search_mail_content/i18n/es_MX.po
odoo/addons/base_search_mail_content/i18n/es_VE.po
odoo/addons/base_search_mail_content/i18n/et.po
odoo/addons/base_search_mail_content/i18n/eu.po
odoo/addons/base_search_mail_content/i18n/fi.po
odoo/addons/base_search_mail_content/i18n/fr.po
odoo/addons/base_search_mail_content/i18n/fr_CA.po
odoo/addons/base_search_mail_content/i18n/fr_CH.po
odoo/addons/base_search_mail_content/i18n/gl.po
odoo/addons/base_search_mail_content/i18n/hr.po
odoo/addons/base_search_mail_content/i18n/hr_HR.po
odoo/addons/base_search_mail_content/i18n/hu.po
odoo/addons/base_search_mail_content/i18n/it.po
odoo/addons/base_search_mail_content/i18n/ja.po
odoo/addons/base_search_mail_content/i18n/lt.po
odoo/addons/base_search_mail_content/i18n/lv.po
odoo/addons/base_search_mail_content/i18n/mk.po
odoo/addons/base_search_mail_content/i18n/mn.po
odoo/addons/base_search_mail_content/i18n/nb.po
odoo/addons/base_search_mail_content/i18n/nb_NO.po
odoo/addons/base_search_mail_content/i18n/nl.po
odoo/addons/base_search_mail_content/i18n/nl_BE.po
odoo14_addon_base_search_mail_content-14.0.1.0.1.dist-info/METADATA
odoo14_addon_base_search_mail_content-14.0.1.0.1.dist-info/WHEEL
odoo14_addon_base_search_mail_content-14.0.1.0.1.dist-info/top_level.txt
odoo14_addon_base_search_mail_content-14.0.1.0.1.dist-info/RECORD
